mod77/__init__.py
mod77/accesspoint.py
mod77/audio.py
mod77/fingerprint.py
mod77/gps.py
mod77/led.py
mod77/photo_video.py
mod77/rfid.py
mod77/telegram.py
mod77/time_1.py
mod77/zero.py
pylibrnew-0.0.1.dist-info/LICENSE
pylibrnew-0.0.1.dist-info/METADATA
pylibrnew-0.0.1.dist-info/WHEEL
pylibrnew-0.0.1.dist-info/top_level.txt
pylibrnew-0.0.1.dist-info/RECORD
